Workbook

Sheet Costs 15%
B3: Battery Bank NMC
C4: Capacity (kWh) | D4: Lowest Cost ($/kWh) | E4: Highest Cost ($/kWh) | F4: Average Cost ($/kWh) | G4: Total Cost ($)
B5: NMC | C5: 2800 | D5: 600 | E5: 1000 | F5: =(D5+E5)/2 -> 800 | G5: =F5*C5 -> 2240000
B6: LFP | C6: 2800 | D6: 300 | E6: 600 | F6: =(D6+E6)/2 -> 450 | G6: =F6*C6 -> 1260000
B7: LTO | C7: 2800 | D7: 800 | E7: 1200 | F7: =(D7+E7)/2 -> 1000 | G7: =F7*C7 -> 2800000
B8: DC/DC Converters
B9: Units | C9: Nominal Power per unit (kW) | D9: Lowest Cost ($/kW) | E9: Highest Cost ($/kW) | F9: Average Cost ($/kW) | G9: Total Cost ($)
B10: 4 | C10: 150 | D10: 100 | E10: 400 | F10: =(D10+E10)/2 -> 250 | G10: =B10*C10*F10 -> 150000
B11: Inverters and Drives
C12: Units | D12: Nominal Power per unit (kW) | E12: Lowest Cost ($/kW) | F12: Highest Cost ($/kW) | G12: Average Cost ($/kW) | H12: Total Cost ($)
B13: Inverter | C13: 2 | D13: 300 | E13: 250 | F13: 450 | G13: =(E13+F13)/2 -> 350 | H13: =C13*D13*G13 -> 210000
B14: Drive | C14: 2 | D14: 1000 | E14: 120 | F14: 250 | G14: =(E14+F14)/2 -> 185 | H14: =C14*D14*G14 -> 370000
B15: Main Genset
C16: Units | D16: Nominal Power per unit (kW) | E16: Lowest Cost ($/kW) | F16: Highest Cost ($/kW) | G16: Average Cost ($/kW) | H16: Total Cost ($)
C17: 1 | D17: 2000 | E17: 75 | F17: 750 | G17: =(E17+F17)/2 -> 412.5 | H17: =C17*D17*G17 -> 825000
B18: Electric Motors
C19: Units | D19: Nominal Power per unit (kW) | E19: Lowest Cost ($/kW) | F19: Highest Cost ($/kW) | G19: Average Cost ($/kW) | H19: Total Cost ($)
B20: Electric Motors | C20: 2 | D20: 1000 | E20: 90 | F20: 250 | G20: =(E20+F20)/2 -> 170 | H20: =C20*D20*G20 -> 340000
B21: Integration/Cabling/Equipment
E22: Lowest Cost ($) | F22: Highest Cost ($) | G22: Average Cost ($) | H22: Total Cost ($)
E23: 100000 | F23: 175000 | G23: =(E23+F23)/2 -> 137500 | H23: =G23 -> 137500
B24: Fire/Safety Systems
E25: Lowest Cost ($) | F25: Highest Cost ($) | G25: Average Cost ($) | H25: Total Cost ($)
E26: 50000 | F26: 80000 | G26: =(E26+F26)/2 -> 65000 | H26: =G26 -> 65000

Sheet CAPEX 15%
B3: NMC | E3: LFP | H3: LTO
B4: Batt Bank | C4: ='Costs 15%'!G5 -> 2240000 | E4: Batt Bank | F4: ='Costs 15%'!G6 -> 1260000 | H4: Batt Bank | I4: ='Costs 15%'!G7 -> 2800000
B5: DC/DC | C5: ='Costs 15%'!$G$10 -> 150000 | E5: DC/DC | F5: ='Costs 15%'!$G$10 -> 150000 | H5: DC/DC | I5: ='Costs 15%'!$G$10 -> 150000
B6: Inverters/Drives | C6: ='Costs 15%'!$H$13+'Costs 15%'!$H$14 -> 580000 | E6: Inverters/Drives | F6: ='Costs 15%'!$H$13+'Costs 15%'!$H$14 -> 580000 | H6: Inverters/Drives | I6: ='Costs 15%'!$H$13+'Costs 15%'!$H$14 -> 580000
B7: Main Genset | C7: ='Costs 15%'!$H$17 -> 825000 | E7: Main Genset | F7: ='Costs 15%'!$H$17 -> 825000 | H7: Main Genset | I7: ='Costs 15%'!$H$17 -> 825000
B8: Electric Motors | C8: ='Costs 15%'!$H$20 -> 340000 | E8: Electric Motors | F8: ='Costs 15%'!$H$20 -> 340000 | H8: Electric Motors | I8: ='Costs 15%'!$H$20 -> 340000
B9: General Equipments/elements | C9: ='Costs 15%'!$H$23 -> 137500 | E9: General Equipments/elements | F9: ='Costs 15%'!$H$23 -> 137500 | H9: General Equipments/elements | I9: ='Costs 15%'!$H$23 -> 137500
B10: Fire security system | C10: ='Costs 15%'!$H$26 -> 65000 | E10: Fire security system | F10: ='Costs 15%'!$H$26 -> 65000 | H10: Fire security system | I10: ='Costs 15%'!$H$26 -> 65000
B11: Costo Bruto | C11: =SUM(C4:C10) -> 4337500 | E11: Costo Bruto | F11: =SUM(F4:F10) -> 3357500 | H11: Costo Bruto | I11: =SUM(I4:I10) -> 4897500
B12: Engineering | C12: =C11*0.035 -> 151812.5 | E12: Engineering | F12: =F11*0.035 -> 117512.5 | H12: Engineering | I12: =I11*0.035 -> 171412.5
B13: Goverment grants (20%-40%) | C13: =C11*C17 -> 433750 | E13: Goverment grants (20%-40%) | F13: =F11*C17 -> 335750 | H13: Goverment grants (20%-40%) | I13: =I11*C17 -> 489750
B14: Costo Total | C14: =C11+C12-C13 -> 4055562.5 | E14: Costo Total | F14: =F11-F13-F12 -> 2904237.5 | H14: Costo Total | I14: =I11-I13-I12 -> 4236337.5
B17: Percentage of the cost subsidized by the government | C17: 0.1

Sheet OPEX 15%
B2: Conventional Tug | E2: Hybrid Tug - NMC | H2: Hybrid Tug - LFP | K2: Hybrid Tug - LTO
B3: Lowest annual fuel consumption (L) | C3: =5366*365 -> 1958590 | E3: Lowest annual fuel consumption (L) | F3: =2406*365 -> 878190 | H3: Lowest annual fuel consumption (L) | I3: =2406*365 -> 878190 | K3: Lowest annual fuel consumption (L) | L3: =2406*365 -> 878190
B4: Highest annual fuel consumption (L) | C4: =6385*365 -> 2330525 | E4: Highest annual fuel consumption (L) | F4: =4268*365 -> 1557820 | H4: Highest annual fuel consumption (L) | I4: =4268*365 -> 1557820 | K4: Highest annual fuel consumption (L) | L4: =4268*365 -> 1557820
B5: Average annual fuel consumption (L) | C5: =(C3+C4)/2 -> 2144557.5 | E5: Average annual fuel consumption (L) | F5: =(F3+F4)/2 -> 1218005 | H5: Average annual fuel consumption (L) | I5: =(I3+I4)/2 -> 1218005 | K5: Average annual fuel consumption (L) | L5: =(L3+L4)/2 -> 1218005
B6: Lowest annual CO2 emissions generated (t) | C6: =14.3*365 -> 5219.5 | E6: Lowest annual CO2 emissions generated (t) | F6: =6.4*365 -> 2336 | H6: Lowest annual CO2 emissions generated (t) | I6: =6.4*365 -> 2336 | K6: Lowest annual CO2 emissions generated (t) | L6: =6.4*365 -> 2336
B7: Highest annual CO2 emissions generated (t) | C7: =17*365 -> 6205 | E7: Highest annual CO2 emissions generated (t) | F7: =11.4*365 -> 4161 | H7: Highest annual CO2 emissions generated (t) | I7: =11.4*365 -> 4161 | K7: Highest annual CO2 emissions generated (t) | L7: =11.4*365 -> 4161
B8: Average annual CO2 emissions generated (t) | C8: =(C6+C7)/2 -> 5712.25 | E8: Average annual CO2 emissions generated (t) | F8: =(F6+F7)/2 -> 3248.5 | H8: Average annual CO2 emissions generated (t) | I8: =(I6+I7)/2 -> 3248.5 | K8: Average annual CO2 emissions generated (t) | L8: =(L6+L7)/2 -> 3248.5
B9: Fuel Cost ($/L) | C9: =0.8 -> 0.8 | E9: Fuel Cost ($/L) | F9: =0.8 -> 0.8 | H9: Fuel Cost ($/L) | I9: =0.8 -> 0.8 | K9: Fuel Cost ($/L) | L9: =0.8 -> 0.8
B10: Total fuel cost ($/year) | C10: =C5*C9 -> 1715646 | E10: Total fuel cost ($/year) | F10: =F5*F9 -> 974404 | H10: Total fuel cost ($/year) | I10: =I5*I9 -> 974404 | K10: Total fuel cost ($/year) | L10: =L5*L9 -> 974404
B11: Electricity | C11: 0 | E11: Electricity | F11: 30000 | H11: Electricity | I11: 30000 | K11: Electricity | L11: 30000
B12: Engine Maintenance | C12: 40000 | E12: Engine Maintenance | F12: 20000 | H12: Engine Maintenance | I12: 20000 | K12: Engine Maintenance | L12: 20000
B13: Battery Replacement | C13: 0 | E13: Battery Maintenance | F13: ='Costs 15%'!G5/15 -> 149333.33 | H13: Battery Maintenance | I13: ='Costs 15%'!G6/15 -> 84000 | K13: Battery Maintenance
B14: Carbon Tax ($50/ton) | C14: =50*C8 -> 285612.5 | E14: Carbon Tax ($50/ton) | F14: =50*F8 -> 162425 | H14: Carbon Tax ($50/ton) | I14: =50*I8 -> 162425 | K14: Carbon Tax ($50/ton) | L14: =50*L8 -> 162425
B15: Total OPEX | C15: =SUM(C10:C14) -> 2041258.5 | E15: Total OPEX - NMC | F15: =SUM(F10:F14) -> 1336162.3 | H15: Total OPEX - LFP | I15: =SUM(I10:I14) -> 1270829 | K15: Total OPEX - LTO | L15: =SUM(L10:L14) -> 1186829
E17: OPEX Conventional Tug | F17: =C15 -> 2041258.5 | H17: OPEX Conventional Tug | I17: =C15 -> 2041258.5 | K17: OPEX Conventional Tug | L17: =C15 -> 2041258.5
E18: OPEX Hybrid Tug | F18: =F15 -> 1336162.3 | H18: OPEX Hybrid Tug | I18: =I15 -> 1270829 | K18: OPEX Hybrid Tug | L18: =L15 -> 1186829
E19: Annual profit | F19: =F17-F18 -> 705096.17 | H19: Annual profit | I19: =I17-I18 -> 770429.5 | K19: Annual profit | L19: =L17-L18 -> 854429.5

Sheet VAN 15%
H1: 10 años | K1: 15 años | N1: 20 años
B2: Lifespan | C2: 20 | E2: Cost NMC | F2: ='CAPEX 15%'!C14 -> 4055562.5 | H2: VAN NMC | I2: =SUM($C$9:$L$9)-F2 -> 675690.17 | K2: VAN NMC | L2: =SUM($C$9:$L$9)+SUM($C$14:$G$14)-F2 -> 1979693.1 | N2: VAN NMC | O2: =SUM($C$9:$L$9)+SUM($C$14:$L$14)-F2 -> 2867175.6
B3: Discount Rate (%) | C3: 0.08 | E3: Cost LFP | F3: ='CAPEX 15%'!F14 -> 2904237.5 | H3: VAN LFP | I3: =SUM($C$10:$L$10)-F3 -> 2265407.2 | K3: VAN LFP | L3: =SUM($C$10:$L$10)+SUM($C$15:$G$15)-F3 -> 3690237.4 | N3: VAN LFP | O3: =SUM($C$10:$L$10)+SUM($C$15:$L$15)-F3 -> 4659952.9
B4: Anual Profit NMC ($) | C4: ='OPEX 15%'!F19 -> 705096.17 | E4: Cost LTO | F4: ='CAPEX 15%'!I14 -> 4236337.5 | H4: VAN LTO | I4: =SUM($C$11:$L$11)-F4 -> 1496954 | K4: VAN LTO | L4: =SUM($C$11:$L$11)+SUM($C$16:$G$16)-F4 -> 3077133.6 | N4: VAN LTO | O4: =SUM($C$11:$L$11)+SUM($C$16:$L$16)-F4 -> 4152577.3
B5: Anual Profit LFP ($) | C5: ='OPEX 15%'!I19 -> 770429.5
B6: Anual Profit LTO ($) | C6: ='OPEX 15%'!L19 -> 854429.5
C7: Years
C8: 1 | D8: 2 | E8: 3 | F8: 4 | G8: 5 | H8: 6 | I8: 7 | J8: 8 | K8: 9 | L8: 10
B9: NMC | C9: =$C$4/((1+$C$3)^C8) -> 652866.82 | D9: =$C$4/((1+$C$3)^D8) -> 604506.32 | E9: =$C$4/((1+$C$3)^E8) -> 559728.07 | F9: =$C$4/((1+$C$3)^F8) -> 518266.73 | G9: =$C$4/((1+$C$3)^G8) -> 479876.6 | H9: =$C$4/((1+$C$3)^H8) -> 444330.19 | I9: =$C$4/((1+$C$3)^I8) -> 411416.84 | J9: =$C$4/((1+$C$3)^J8) -> 380941.52 | ... L9: =$C$4/((1+$C$3)^L8) -> 326595.95
B10: LFP | C10: =$C$5/((1+$C$3)^C8) -> 713360.65 | D10: =$C$5/((1+$C$3)^D8) -> 660519.12 | E10: =$C$5/((1+$C$3)^E8) -> 611591.78 | F10: =$C$5/((1+$C$3)^F8) -> 566288.68 | G10: =$C$5/((1+$C$3)^G8) -> 524341.37 | H10: =$C$5/((1+$C$3)^H8) -> 485501.27 | I10: =$C$5/((1+$C$3)^I8) -> 449538.21 | J10: =$C$5/((1+$C$3)^J8) -> 416239.09 | ... L10: =$C$5/((1+$C$3)^L8) -> 356857.93
B11: LTO | C11: =$C$6/((1+$C$3)^C8) -> 791138.43 | D11: =$C$6/((1+$C$3)^D8) -> 732535.58 | E11: =$C$6/((1+$C$3)^E8) -> 678273.68 | F11: =$C$6/((1+$C$3)^F8) -> 628031.19 | G11: =$C$6/((1+$C$3)^G8) -> 581510.36 | H11: =$C$6/((1+$C$3)^H8) -> 538435.52 | I11: =$C$6/((1+$C$3)^I8) -> 498551.41 | J11: =$C$6/((1+$C$3)^J8) -> 461621.67 | ... L11: =$C$6/((1+$C$3)^L8) -> 395766.18
C13: 11 | D13: 12 | E13: 13 | F13: 14 | G13: 15 | H13: 16 | I13: 17 | J13: 18 | K13: 19 | L13: 20
B14: NMC | C14: =$C$4/((1+$C$3)^C13) -> 302403.66 | D14: =$C$4/((1+$C$3)^D13) -> 280003.39 | E14: =$C$4/((1+$C$3)^E13) -> 259262.4 | F14: =$C$4/((1+$C$3)^F13) -> 240057.78 | G14: =$C$4/((1+$C$3)^G13) -> 222275.72 | H14: =$C$4/((1+$C$3)^H13) -> 205810.85 | I14: =$C$4/((1+$C$3)^I13) -> 190565.6 | J14: =$C$4/((1+$C$3)^J13) -> 176449.63 | ... L14: =$C$4/((1+$C$3)^L13) -> 151277.12
B15: LFP | C15: =$C$5/((1+$C$3)^C13) -> 330424.01 | D15: =$C$5/((1+$C$3)^D13) -> 305948.15 | E15: =$C$5/((1+$C$3)^E13) -> 283285.33 | F15: =$C$5/((1+$C$3)^F13) -> 262301.23 | G15: =$C$5/((1+$C$3)^G13) -> 242871.51 | H15: =$C$5/((1+$C$3)^H13) -> 224881.03 | I15: =$C$5/((1+$C$3)^I13) -> 208223.17 | J15: =$C$5/((1+$C$3)^J13) -> 192799.23 | ... L15: =$C$5/((1+$C$3)^L13) -> 165294.27
B16: LTO | C16: =$C$6/((1+$C$3)^C13) -> 366450.17 | D16: =$C$6/((1+$C$3)^D13) -> 339305.71 | E16: =$C$6/((1+$C$3)^E13) -> 314171.95 | F16: =$C$6/((1+$C$3)^F13) -> 290899.96 | G16: =$C$6/((1+$C$3)^G13) -> 269351.81 | H16: =$C$6/((1+$C$3)^H13) -> 249399.83 | I16: =$C$6/((1+$C$3)^I13) -> 230925.77 | J16: =$C$6/((1+$C$3)^J13) -> 213820.15 | ... L16: =$C$6/((1+$C$3)^L13) -> 183316.32

Sheet TIR 15%
E1: 10 años | H1: 15 años | K1: 20 años
B2: Anual Profit NMC ($) | C2: ='OPEX 15%'!F19 -> 705096.17 | E2: TIR NMC | F2: =IRR(B9:L9) -> 0.1156704 | H2: TIR NMC | I2: =IRR(B9:Q9) -> 0.15342482 | K2: TIR NMC | L2: =IRR(B9:V9) -> 0.16576906
B3: Anual Profit LFP ($) | C3: ='OPEX 15%'!I19 -> 770429.5 | E3: TIR LFP | F3: =IRR(B14:L14) -> 0.232474 | H3: TIR LFP | I3: =IRR(B14:Q14) -> 0.25665908 | K3: TIR LFP | L3: =IRR(B14:V14) -> 0.26278237
B4: Anual Profit LTO ($) | C4: ='OPEX 15%'!L19 -> 854429.5 | E4: TIR LTO | F4: =IRR(B19:L19) -> 0.15320353 | H4: TIR LTO | I4: =IRR(B19:Q19) -> 0.18609987 | K4: TIR LTO | L4: =IRR(B19:V19) -> 0.19607328
C7: NMC Batt Bank
B8: 0 | C8: 1 | D8: 2 | E8: 3 | F8: 4 | G8: 5 | H8: 6 | I8: 7 | J8: 8 | K8: 9 | L8: 10 | M8: 11 | N8: 12 | O8: 13 | P8: 14 | Q8: 15 | R8: 16 | S8: 17 | T8: 18 | U8: 19 | V8: 20
B9: =-'CAPEX 15%'!C14 -> -4055562.5 | C9: =$C$2 -> 705096.17 | D9: =$C$2 -> 705096.17 | E9: =$C$2 -> 705096.17 | F9: =$C$2 -> 705096.17 | G9: =$C$2 -> 705096.17 | H9: =$C$2 -> 705096.17 | I9: =$C$2 -> 705096.17 | J9: =$C$2 -> 705096.17 | ... V9: =$C$2 -> 705096.17
C12: LFP Batt Bank
B13: 0 | C13: 1 | D13: 2 | E13: 3 | F13: 4 | G13: 5 | H13: 6 | I13: 7 | J13: 8 | K13: 9 | L13: 10 | M13: 11 | N13: 12 | O13: 13 | P13: 14 | Q13: 15 | R13: 16 | S13: 17 | T13: 18 | U13: 19 | V13: 20
B14: =-'CAPEX 15%'!F14 -> -2904237.5 | C14: =$C$3 -> 770429.5 | D14: =$C$3 -> 770429.5 | E14: =$C$3 -> 770429.5 | F14: =$C$3 -> 770429.5 | G14: =$C$3 -> 770429.5 | H14: =$C$3 -> 770429.5 | I14: =$C$3 -> 770429.5 | J14: =$C$3 -> 770429.5 | ... V14: =$C$3 -> 770429.5
C17: LTO Batt Bank
B18: 0 | C18: 1 | D18: 2 | E18: 3 | F18: 4 | G18: 5 | H18: 6 | I18: 7 | J18: 8 | K18: 9 | L18: 10 | M18: 11 | N18: 12 | O18: 13 | P18: 14 | Q18: 15 | R18: 16 | S18: 17 | T18: 18 | U18: 19 | V18: 20
B19: =-'CAPEX 15%'!I14 -> -4236337.5 | C19: =$C$4 -> 854429.5 | D19: =$C$4 -> 854429.5 | E19: =$C$4 -> 854429.5 | F19: =$C$4 -> 854429.5 | G19: =$C$4 -> 854429.5 | H19: =$C$4 -> 854429.5 | I19: =$C$4 -> 854429.5 | J19: =$C$4 -> 854429.5 | ... V19: =$C$4 -> 854429.5

Sheet ROI 15%
B2: Lifespan | C2: 20 | E2: Cost NMC | F2: ='CAPEX 15%'!C14 -> 4055562.5 | H2: ROI NMC | I2: =F2/$C$4 -> 5.7517863
B3: Discount Rate (%) | C3: 0 | E3: Cost LFP | F3: ='CAPEX 15%'!F14 -> 2904237.5 | H3: ROI LFP | I3: =F3/$C$5 -> 3.7696343
B4: Annual Profit NMC ($) | C4: ='OPEX 15%'!F19 -> 705096.17 | E4: Cost LTO | F4: ='CAPEX 15%'!I14 -> 4236337.5 | H4: ROI LTO | I4: =F4/$C$6 -> 4.958089
B5: Anual Profit LFP ($) | C5: ='OPEX 15%'!I19 -> 770429.5
B6: Anual Profit LTO ($) | C6: ='OPEX 15%'!L19 -> 854429.5
C7: ROI NMC | P7: ROI NMC
B8: 0 | C8: 1 | D8: 2 | E8: 3 | F8: 4 | G8: 5 | H8: 6 | I8: 7 | J8: 8 | K8: 9 | L8: 10 | P8: 1 | Q8: 2 | R8: 3 | S8: 4 | T8: 5 | U8: 6 | V8: 7 | W8: 8 | X8: 9 | Y8: 10
B9: =-F2 -> -4055562.5 | C9: =$C$4*C8-$F$2 -> -3350466.3 | D9: =$C$4*D8-$F$2 -> -2645370.2 | E9: =$C$4*E8-$F$2 -> -1940274 | F9: =$C$4*F8-$F$2 -> -1235177.8 | G9: =$C$4*G8-$F$2 -> -530081.67 | H9: =$C$4*H8-$F$2 -> 175014.5 | I9: =$C$4*I8-$F$2 -> 880110.67 | J9: =$C$4*J8-$F$2 -> 1585206.8 | ... L9: =$C$4*L8-$F$2 -> 2995399.2 | P9: =(C9/$F$2) -> -0.82614097 | Q9: =(D9/$F$2) -> -0.65228194 | R9: =(E9/$F$2) -> -0.47842291 | S9: =(F9/$F$2) -> -0.30456388 | T9: =(G9/$F$2) -> -0.13070484 | U9: =(H9/$F$2) -> 0.043154186 | V9: =(I9/$F$2) -> 0.21701322 | W9: =(J9/$F$2) -> 0.39087225 | ... Y9: =(L9/$F$2) -> 0.73859031
C12: 11 | D12: 12 | E12: 13 | F12: 14 | G12: 15 | H12: 16 | I12: 17 | J12: 18 | K12: 19 | L12: 20 | P12: 11 | Q12: 12 | R12: 13 | S12: 14 | T12: 15 | U12: 16 | V12: 17 | W12: 18 | X12: 19 | Y12: 20
C13: =$C$4*C12-$F$2 -> 3700495.3 | D13: =$C$4*D12-$F$2 -> 4405591.5 | E13: =$C$4*E12-$F$2 -> 5110687.7 | F13: =$C$4*F12-$F$2 -> 5815783.8 | G13: =$C$4*G12-$F$2 -> 6520880 | H13: =$C$4*H12-$F$2 -> 7225976.2 | I13: =$C$4*I12-$F$2 -> 7931072.3 | J13: =$C$4*J12-$F$2 -> 8636168.5 | ... L13: =$C$4*L12-$F$2 -> 10046361 | P13: =C13/$F$2 -> 0.91244934 | Q13: =D13/$F$2 -> 1.0863084 | R13: =E13/$F$2 -> 1.2601674 | S13: =F13/$F$2 -> 1.4340264 | T13: =G13/$F$2 -> 1.6078855 | U13: =H13/$F$2 -> 1.7817445 | V13: =I13/$F$2 -> 1.9556035 | W13: =J13/$F$2 -> 2.1294626 | ... Y13: =L13/$F$2 -> 2.4771806
C16: ROI LFP | P16: ROI LFP
B17: 0 | C17: 1 | D17: 2 | E17: 3 | F17: 4 | G17: 5 | H17: 6 | I17: 7 | J17: 8 | K17: 9 | L17: 10 | P17: 1 | Q17: 2 | R17: 3 | S17: 4 | T17: 5 | U17: 6 | V17: 7 | W17: 8 | X17: 9 | Y17: 10
B18: =-F3 -> -2904237.5 | C18: =$C$5/((1+$C$3)^C17)+B18 -> -2133808 | D18: =$C$5/((1+$C$3)^D17)+C18 -> -1363378.5 | E18: =$C$5/((1+$C$3)^E17)+D18 -> -592949 | F18: =$C$5/((1+$C$3)^F17)+E18 -> 177480.5 | G18: =$C$5/((1+$C$3)^G17)+F18 -> 947910 | H18: =$C$5/((1+$C$3)^H17)+G18 -> 1718339.5 | I18: =$C$5/((1+$C$3)^I17)+H18 -> 2488769 | J18: =$C$5/((1+$C$3)^J17)+I18 -> 3259198.5 | ... L18: =$C$5/((1+$C$3)^L17)+K18 -> 4800057.5 | P18: =C18/$F$3 -> -0.73472228 | Q18: =D18/$F$3 -> -0.46944456 | R18: =E18/$F$3 -> -0.20416684 | S18: =F18/$F$3 -> 0.061110877 | T18: =G18/$F$3 -> 0.3263886 | U18: =H18/$F$3 -> 0.59166632 | V18: =I18/$F$3 -> 0.85694403 | W18: =J18/$F$3 -> 1.1222218 | ... Y18: =L18/$F$3 -> 1.6527772
C21: 11 | D21: 12 | E21: 13 | F21: 14 | G21: 15 | H21: 16 | I21: 17 | J21: 18 | K21: 19 | L21: 20 | P21: 11 | Q21: 12 | R21: 13 | S21: 14 | T21: 15 | U21: 16 | V21: 17 | W21: 18 | X21: 19 | Y21: 20
C22: =$C$5/((1+$C$3)^C21)+L18 -> 5570487 | D22: =$C$5/((1+$C$3)^D21)+C22 -> 6340916.5 | E22: =$C$5/((1+$C$3)^E21)+D22 -> 7111346 | F22: =$C$5/((1+$C$3)^F21)+E22 -> 7881775.5 | G22: =$C$5/((1+$C$3)^G21)+F22 -> 8652205 | H22: =$C$5/((1+$C$3)^H21)+G22 -> 9422634.5 | I22: =$C$5/((1+$C$3)^I21)+H22 -> 10193064 | J22: =$C$5/((1+$C$3)^J21)+I22 -> 10963494 | K22: =$C$5/((1+$C$3)^K21)+J22 -> 11733923 | L22: =$C$5/((1+$C$3)^L21)+K22 -> 12504352 | P22: =C22/$F$3 -> 1.9180549 | Q22: =D22/$F$3 -> 2.1833326 | R22: =E22/$F$3 -> 2.4486103 | S22: =F22/$F$3 -> 2.7138881 | T22: =G22/$F$3 -> 2.9791658 | U22: =H22/$F$3 -> 3.2444435 | V22: =I22/$F$3 -> 3.5097212 | W22: =J22/$F$3 -> 3.7749989 | ... Y22: =L22/$F$3 -> 4.3055544
C26: ROI LTO | P26: ROI LTO
B27: 0 | C27: 1 | D27: 2 | E27: 3 | F27: 4 | G27: 5 | H27: 6 | I27: 7 | J27: 8 | K27: 9 | L27: 10 | P27: 1 | Q27: 2 | R27: 3 | S27: 4 | T27: 5 | U27: 6 | V27: 7 | W27: 8 | X27: 9 | Y27: 10
B28: =-F4 -> -4236337.5 | C28: =$C$6/((1+$C$3)^C27)+B28 -> -3381908 | D28: =$C$6/((1+$C$3)^D27)+C28 -> -2527478.5 | E28: =$C$6/((1+$C$3)^E27)+D28 -> -1673049 | F28: =$C$6/((1+$C$3)^F27)+E28 -> -818619.5 | G28: =$C$6/((1+$C$3)^G27)+F28 -> 35810 | H28: =$C$6/((1+$C$3)^H27)+G28 -> 890239.5 | I28: =$C$6/((1+$C$3)^I27)+H28 -> 1744669 | J28: =$C$6/((1+$C$3)^J27)+I28 -> 2599098.5 | ... L28: =$C$6/((1+$C$3)^L27)+K28 -> 4307957.5 | P28: =C28/$F$4 -> -0.79830939 | Q28: =D28/$F$4 -> -0.59661878 | R28: =E28/$F$4 -> -0.39492817 | S28: =F28/$F$4 -> -0.19323755 | T28: =G28/$F$4 -> 0.0084530564 | U28: =H28/$F$4 -> 0.21014367 | V28: =I28/$F$4 -> 0.41183428 | W28: =J28/$F$4 -> 0.61352489 | ... Y28: =L28/$F$4 -> 1.0169061
C31: 11 | D31: 12 | E31: 13 | F31: 14 | G31: 15 | H31: 16 | I31: 17 | J31: 18 | K31: 19 | L31: 20 | P31: 11 | Q31: 12 | R31: 13 | S31: 14 | T31: 15 | U31: 16 | V31: 17 | W31: 18 | X31: 19 | Y31: 20
C32: =$C$6/((1+$C$3)^C31)+L28 -> 5162387 | D32: =$C$6/((1+$C$3)^D31)+C32 -> 6016816.5 | E32: =$C$6/((1+$C$3)^E31)+D32 -> 6871246 | F32: =$C$6/((1+$C$3)^F31)+E32 -> 7725675.5 | G32: =$C$6/((1+$C$3)^G31)+F32 -> 8580105 | H32: =$C$6/((1+$C$3)^H31)+G32 -> 9434534.5 | I32: =$C$6/((1+$C$3)^I31)+H32 -> 10288964 | J32: =$C$6/((1+$C$3)^J31)+I32 -> 11143394 | K32: =$C$6/((1+$C$3)^K31)+J32 -> 11997823 | L32: =$C$6/((1+$C$3)^L31)+K32 -> 12852252 | P32: =C32/$F$4 -> 1.2185967 | Q32: =D32/$F$4 -> 1.4202873 | R32: =E32/$F$4 -> 1.6219779 | S32: =F32/$F$4 -> 1.8236686 | T32: =G32/$F$4 -> 2.0253592 | U32: =H32/$F$4 -> 2.2270498 | V32: =I32/$F$4 -> 2.4287404 | W32: =J32/$F$4 -> 2.630431 | ... Y32: =L32/$F$4 -> 3.0338122
