Workbook

Sheet Costs 25%
B3: Battery Bank NMC
C4: Capacity (kWh) | D4: Lowest Cost ($/kWh) | E4: Highest Cost ($/kWh) | F4: Average Cost ($/kWh) | G4: Total Cost ($)
B5: NMC | C5: 6300 | D5: 600 | E5: 1000 | F5: =(D5+E5)/2 -> 800 | G5: =F5*C5 -> 5040000
B6: LFP | C6: 6300 | D6: 300 | E6: 600 | F6: =(D6+E6)/2 -> 450 | G6: =F6*C6 -> 2835000
B7: LTO | C7: 6300 | D7: 800 | E7: 1200 | F7: =(D7+E7)/2 -> 1000 | G7: =F7*C7 -> 6300000
B8: DC/DC Converters
B9: Units | C9: Nominal Power per unit (kW) | D9: Lowest Cost ($/kW) | E9: Highest Cost ($/kW) | F9: Average Cost ($/kW) | G9: Total Cost ($)
B10: 4 | C10: 250 | D10: 100 | E10: 400 | F10: =(D10+E10)/2 -> 250 | G10: =B10*C10*F10 -> 250000
B11: Inverters and Drives
C12: Units | D12: Nominal Power per unit (kW) | E12: Lowest Cost ($/kW) | F12: Highest Cost ($/kW) | G12: Average Cost ($/kW) | H12: Total Cost ($)
B13: Inverter | C13: 2 | D13: 500 | E13: 250 | F13: 450 | G13: =(E13+F13)/2 -> 350 | H13: =C13*D13*G13 -> 350000
B14: Drive | C14: 2 | D14: 1000 | E14: 120 | F14: 250 | G14: =(E14+F14)/2 -> 185 | H14: =C14*D14*G14 -> 370000
B15: Main Genset
C16: Units | D16: Nominal Power per unit (kW) | E16: Lowest Cost ($/kW) | F16: Highest Cost ($/kW) | G16: Average Cost ($/kW) | H16: Total Cost ($)
C17: 1 | D17: 2000 | E17: 75 | F17: 750 | G17: =(E17+F17)/2 -> 412.5 | H17: =C17*D17*G17 -> 825000
B18: Electric Motors
C19: Units | D19: Nominal Power per unit (kW) | E19: Lowest Cost ($/kW) | F19: Highest Cost ($/kW) | G19: Average Cost ($/kW) | H19: Total Cost ($)
B20: Electric Motors | C20: 2 | D20: 1000 | E20: 90 | F20: 250 | G20: =(E20+F20)/2 -> 170 | H20: =C20*D20*G20 -> 340000
B21: Integration/Cabling/Equipment
E22: Lowest Cost ($) | F22: Highest Cost ($) | G22: Average Cost ($) | H22: Total Cost ($)
E23: 100000 | F23: 175000 | G23: =(E23+F23)/2 -> 137500 | H23: =G23 -> 137500
B24: Fire/Safety Systems
E25: Lowest Cost ($) | F25: Highest Cost ($) | G25: Average Cost ($) | H25: Total Cost ($)
E26: 50000 | F26: 80000 | G26: =(E26+F26)/2 -> 65000 | H26: =G26 -> 65000

Sheet CAPEX 25%
B3: NMC | E3: LFP | H3: LTO
B4: Batt Bank | C4: ='Costs 25%'!G5 -> 5040000 | E4: Batt Bank | F4: ='Costs 25%'!G6 -> 2835000 | H4: Batt Bank | I4: ='Costs 25%'!G7 -> 6300000
B5: DC/DC | C5: ='Costs 25%'!$G$10 -> 250000 | E5: DC/DC | F5: ='Costs 25%'!$G$10 -> 250000 | H5: DC/DC | I5: ='Costs 25%'!$G$10 -> 250000
B6: Inverters/Drives | C6: ='Costs 25%'!$H$13+'Costs 25%'!$H$14 -> 720000 | E6: Inverters/Drives | F6: ='Costs 25%'!$H$13+'Costs 25%'!$H$14 -> 720000 | H6: Inverters/Drives | I6: ='Costs 25%'!$H$13+'Costs 25%'!$H$14 -> 720000
B7: Main Genset | C7: ='Costs 25%'!$H$17 -> 825000 | E7: Main Genset | F7: ='Costs 25%'!$H$17 -> 825000 | H7: Main Genset | I7: ='Costs 25%'!$H$17 -> 825000
B8: Electric Motors | C8: ='Costs 25%'!$H$20 -> 340000 | E8: Electric Motors | F8: ='Costs 25%'!$H$20 -> 340000 | H8: Electric Motors | I8: ='Costs 25%'!$H$20 -> 340000
B9: General Equipments/elements | C9: ='Costs 25%'!$H$23 -> 137500 | E9: General Equipments/elements | F9: ='Costs 25%'!$H$23 -> 137500 | H9: General Equipments/elements | I9: ='Costs 25%'!$H$23 -> 137500
B10: Fire security system | C10: ='Costs 25%'!$H$26 -> 65000 | E10: Fire security system | F10: ='Costs 25%'!$H$26 -> 65000 | H10: Fire security system | I10: ='Costs 25%'!$H$26 -> 65000
B11: Costo Bruto | C11: =SUM(C4:C10) -> 7377500 | E11: Costo Bruto | F11: =SUM(F4:F10) -> 5172500 | H11: Costo Bruto | I11: =SUM(I4:I10) -> 8637500
B12: Engineering | C12: =C11*0.035 -> 258212.5 | E12: Engineering | F12: =F11*0.035 -> 181037.5 | H12: Engineering | I12: =I11*0.035 -> 302312.5
B13: Goverment grants (20%-40%) | C13: =C11*C17 -> 737750 | E13: Goverment grants (20%-40%) | F13: =F11*C17 -> 517250 | H13: Goverment grants (20%-40%) | I13: =I11*C17 -> 863750
B14: Costo Total | C14: =C11-C13+C12 -> 6897962.5 | E14: Costo Total | F14: =F11-F13+F12 -> 4836287.5 | H14: Costo Total | I14: =I11-I13+I12 -> 8076062.5
B17: Percentage of the cost subsidized by the government | C17: 0.1

Sheet OPEX 25%
B2: Conventional Tug | E2: Hybrid Tug - NMC | H2: Hybrid Tug - LFP | K2: Hybrid Tug - LTO
B3: Lowest annual fuel consumption (L) | C3: =5366*365 -> 1958590 | E3: Lowest annual fuel consumption (L) | F3: =1929*365 -> 704085 | H3: Lowest annual fuel consumption (L) | I3: =1929*365 -> 704085 | K3: Lowest annual fuel consumption (L) | L3: =1929*365 -> 704085
B4: Highest annual fuel consumption (L) | C4: =6385*365 -> 2330525 | E4: Highest annual fuel consumption (L) | F4: =4030*365 -> 1470950 | H4: Highest annual fuel consumption (L) | I4: =4030*365 -> 1470950 | K4: Highest annual fuel consumption (L) | L4: =4030*365 -> 1470950
B5: Average annual fuel consumption (L) | C5: =(C3+C4)/2 -> 2144557.5 | E5: Average annual fuel consumption (L) | F5: =(F3+F4)/2 -> 1087517.5 | H5: Average annual fuel consumption (L) | I5: =(I3+I4)/2 -> 1087517.5 | K5: Average annual fuel consumption (L) | L5: =(L3+L4)/2 -> 1087517.5
B6: Lowest annual CO2 emissions generated (t) | C6: =14.3*365 -> 5219.5 | E6: Lowest annual CO2 emissions generated (t) | F6: =5.1*365 -> 1861.5 | H6: Lowest annual CO2 emissions generated (t) | I6: =5.1*365 -> 1861.5 | K6: Lowest annual CO2 emissions generated (t) | L6: =5.1*365 -> 1861.5
B7: Highest annual CO2 emissions generated (t) | C7: =17*365 -> 6205 | E7: Highest annual CO2 emissions generated (t) | F7: =10.8*365 -> 3942 | H7: Highest annual CO2 emissions generated (t) | I7: =10.8*365 -> 3942 | K7: Highest annual CO2 emissions generated (t) | L7: =10.8*365 -> 3942
B8: Average annual CO2 emissions generated (t) | C8: =(C6+C7)/2 -> 5712.25 | E8: Average annual CO2 emissions generated (t) | F8: =(F6+F7)/2 -> 2901.75 | H8: Average annual CO2 emissions generated (t) | I8: =(I6+I7)/2 -> 2901.75 | K8: Average annual CO2 emissions generated (t) | L8: =(L6+L7)/2 -> 2901.75
B9: Fuel Cost ($/L) | C9: =0.8 -> 0.8 | E9: Fuel Cost ($/L) | F9: =0.8 -> 0.8 | H9: Fuel Cost ($/L) | I9: =0.8 -> 0.8 | K9: Fuel Cost ($/L) | L9: =0.8 -> 0.8
B10: Total fuel cost ($/year) | C10: =C5*C9 -> 1715646 | E10: Total fuel cost ($/year) | F10: =F5*F9 -> 870014 | H10: Total fuel cost ($/year) | I10: =I5*I9 -> 870014 | K10: Total fuel cost ($/year) | L10: =L5*L9 -> 870014
B11: Electricity | C11: 0 | E11: Electricity | F11: 30000 | H11: Electricity | I11: 30000 | K11: Electricity | L11: 30000
B12: Engine Maintenance | C12: 40000 | E12: Engine Maintenance | F12: 20000 | H12: Engine Maintenance | I12: 20000 | K12: Engine Maintenance | L12: 20000
B13: Battery Replacement | C13: 0 | E13: Battery Maintenance | F13: ='Costs 25%'!G5/15 -> 336000 | H13: Battery Maintenance | I13: ='Costs 25%'!G6/15 -> 189000 | K13: Battery Maintenance
B14: Carbon Tax ($50/ton) | C14: =50*C8 -> 285612.5 | E14: Carbon Tax ($50/ton) | F14: =50*F8 -> 145087.5 | H14: Carbon Tax ($50/ton) | I14: =50*I8 -> 145087.5 | K14: Carbon Tax ($50/ton) | L14: =50*L8 -> 145087.5
B15: Total OPEX | C15: =SUM(C10:C14) -> 2041258.5 | E15: Total OPEX | F15: =SUM(F10:F14) -> 1401101.5 | H15: Total OPEX | I15: =SUM(I10:I14) -> 1254101.5 | K15: Total OPEX | L15: =SUM(L10:L14) -> 1065101.5
E17: OPEX Conventional Tug | F17: =C15 -> 2041258.5 | H17: OPEX Conventional Tug | I17: =C15 -> 2041258.5 | K17: OPEX Conventional Tug | L17: =C15 -> 2041258.5
E18: OPEX Hybrid Tug | F18: =F15 -> 1401101.5 | H18: OPEX Hybrid Tug | I18: =I15 -> 1254101.5 | K18: OPEX Hybrid Tug | L18: =L15 -> 1065101.5
E19: Yearly profit | F19: =F17-F18 -> 640157 | H19: Yearly profit | I19: =I17-I18 -> 787157 | K19: Yearly profit | L19: =L17-L18 -> 976157

Sheet VAN 25%
H1: 10 años | K1: 15 años | N1: 20 años
B2: Lifespan | C2: 20 | E2: CAPEX NMC | F2: ='CAPEX 25%'!C14 -> 6897962.5 | H2: VAN NMC | I2: =SUM($C$9:$L$9)-F2 -> -2602456.9 | K2: VAN NMC | L2: =SUM($C$9:$L$9)+SUM($C$14:$G$14)-F2 -> -1418552.3 | N2: VAN NMC | O2: =SUM($C$9:$L$9)+SUM($C$14:$L$14)-F2 -> -612806.71
B3: Discount Rate (%) | C3: 0.08 | E3: CAPEX LFP | F3: ='CAPEX 25%'!F14 -> 4836287.5 | H3: VAN LFP | I3: =SUM($C$10:$L$10)-F3 -> 445600.04 | K3: VAN LFP | L3: =SUM($C$10:$L$10)+SUM($C$15:$G$15)-F3 -> 1901366.1 | N3: VAN LFP | O3: =SUM($C$10:$L$10)+SUM($C$15:$L$15)-F3 -> 2892136
B4: Annual Profit NMC ($) | C4: ='OPEX 25%'!F19 -> 640157 | E4: CAPEX LTO | F4: ='CAPEX 25%'!I14 -> 8076062.5 | H4: VAN LTO | I4: =SUM($C$11:$L$11)-F4 -> -929144.74 | K4: VAN LTO | L4: =SUM($C$11:$L$11)+SUM($C$16:$G$16)-F4 -> 1040651.1 | N4: VAN LTO | O4: =SUM($C$11:$L$11)+SUM($C$16:$L$16)-F4 -> 2381261
B5: Annual Profit LFP ($) | C5: ='OPEX 25%'!I19 -> 787157
B6: Annual Profit LTO ($) | C6: ='OPEX 25%'!L15 -> 1065101.5
C7: Years
C8: 1 | D8: 2 | E8: 3 | F8: 4 | G8: 5 | H8: 6 | I8: 7 | J8: 8 | K8: 9 | L8: 10
B9: NMC | C9: =$C$4/((1+$C$3)^C8) -> 592737.96 | D9: =$C$4/((1+$C$3)^D8) -> 548831.45 | E9: =$C$4/((1+$C$3)^E8) -> 508177.27 | F9: =$C$4/((1+$C$3)^F8) -> 470534.51 | G9: =$C$4/((1+$C$3)^G8) -> 435680.1 | H9: =$C$4/((1+$C$3)^H8) -> 403407.5 | I9: =$C$4/((1+$C$3)^I8) -> 373525.46 | J9: =$C$4/((1+$C$3)^J8) -> 345856.91 | ... L9: =$C$4/((1+$C$3)^L8) -> 296516.55
B10: LFP | C10: =$C$5/((1+$C$3)^C8) -> 728849.07 | D10: =$C$5/((1+$C$3)^D8) -> 674860.25 | E10: =$C$5/((1+$C$3)^E8) -> 624870.61 | F10: =$C$5/((1+$C$3)^F8) -> 578583.89 | G10: =$C$5/((1+$C$3)^G8) -> 535725.83 | H10: =$C$5/((1+$C$3)^H8) -> 496042.43 | I10: =$C$5/((1+$C$3)^I8) -> 459298.55 | J10: =$C$5/((1+$C$3)^J8) -> 425276.43 | ... L10: =$C$5/((1+$C$3)^L8) -> 364606
B11: LTO | C11: =$C$6/((1+$C$3)^C8) -> 986205.09 | D11: =$C$6/((1+$C$3)^D8) -> 913152.86 | E11: =$C$6/((1+$C$3)^E8) -> 845511.91 | F11: =$C$6/((1+$C$3)^F8) -> 782881.4 | G11: =$C$6/((1+$C$3)^G8) -> 724890.18 | H11: =$C$6/((1+$C$3)^H8) -> 671194.61 | I11: =$C$6/((1+$C$3)^I8) -> 621476.5 | J11: =$C$6/((1+$C$3)^J8) -> 575441.2 | ... L11: =$C$6/((1+$C$3)^L8) -> 493348.08
C13: 11 | D13: 12 | E13: 13 | F13: 14 | G13: 15 | H13: 16 | I13: 17 | J13: 18 | K13: 19 | L13: 20
B14: NMC | C14: =$C$4/((1+$C$3)^C13) -> 274552.36 | D14: =$C$4/((1+$C$3)^D13) -> 254215.15 | E14: =$C$4/((1+$C$3)^E13) -> 235384.4 | F14: =$C$4/((1+$C$3)^F13) -> 217948.52 | G14: =$C$4/((1+$C$3)^G13) -> 201804.18 | H14: =$C$4/((1+$C$3)^H13) -> 186855.73 | I14: =$C$4/((1+$C$3)^I13) -> 173014.56 | J14: =$C$4/((1+$C$3)^J13) -> 160198.67 | ... L14: =$C$4/((1+$C$3)^L13) -> 137344.54
B15: LFP | C15: =$C$5/((1+$C$3)^C13) -> 337598.14 | D15: =$C$5/((1+$C$3)^D13) -> 312590.87 | E15: =$C$5/((1+$C$3)^E13) -> 289436 | F15: =$C$5/((1+$C$3)^F13) -> 267996.29 | G15: =$C$5/((1+$C$3)^G13) -> 248144.71 | H15: =$C$5/((1+$C$3)^H13) -> 229763.62 | I15: =$C$5/((1+$C$3)^I13) -> 212744.1 | J15: =$C$5/((1+$C$3)^J13) -> 196985.28 | ... L15: =$C$5/((1+$C$3)^L13) -> 168883.12
B16: LTO | C16: =$C$6/((1+$C$3)^C13) -> 456803.78 | D16: =$C$6/((1+$C$3)^D13) -> 422966.46 | E16: =$C$6/((1+$C$3)^E13) -> 391635.61 | F16: =$C$6/((1+$C$3)^F13) -> 362625.57 | G16: =$C$6/((1+$C$3)^G13) -> 335764.41 | H16: =$C$6/((1+$C$3)^H13) -> 310892.97 | I16: =$C$6/((1+$C$3)^I13) -> 287863.87 | J16: =$C$6/((1+$C$3)^J13) -> 266540.62 | ... L16: =$C$6/((1+$C$3)^L13) -> 228515.62

Sheet TIR 25%
E1: 10 años | H1: 15 años | K1: 20 años
B2: Annual Profit NMC ($) | C2: ='OPEX 25%'!F19 -> 640157 | E2: TIR NMC | F2: =IRR(B9:L9) -> -0.013353217 | H2: TIR NMC | I2: =IRR(B9:Q9) -> 0.044515286 | K2: TIR NMC | L2: =IRR(B9:V9) -> 0.067825784
B3: Annual Profit LFP ($) | C3: ='OPEX 25%'!I19 -> 787157 | E3: TIR LFP | F3: =IRR(B14:L14) -> 0.10002173 | H3: TIR LFP | I3: =IRR(B14:Q14) -> 0.13994056 | K3: TIR LFP | L3: =IRR(B14:V14) -> 0.15338333
B4: Annual Profit LTO ($) | C4: ='OPEX 25%'!L19 -> 976157 | E4: TIR LTO | F4: =IRR(B19:L19) -> 0.036036556 | H4: TIR LTO | I4: =IRR(B19:Q19) -> 0.085621856 | K4: TIR LTO | L4: =IRR(B19:V19) -> 0.10423191
C7: NMC Batt Bank
B8: 0 | C8: 1 | D8: 2 | E8: 3 | F8: 4 | G8: 5 | H8: 6 | I8: 7 | J8: 8 | K8: 9 | L8: 10 | M8: 11 | N8: 12 | O8: 13 | P8: 14 | Q8: 15 | R8: 16 | S8: 17 | T8: 18 | U8: 19 | V8: 20
B9: =-'CAPEX 25%'!C14 -> -6897962.5 | C9: =$C$2 -> 640157 | D9: =$C$2 -> 640157 | E9: =$C$2 -> 640157 | F9: =$C$2 -> 640157 | G9: =$C$2 -> 640157 | H9: =$C$2 -> 640157 | I9: =$C$2 -> 640157 | J9: =$C$2 -> 640157 | ... V9: =$C$2 -> 640157
C12: LFP Batt Bank
B13: 0 | C13: 1 | D13: 2 | E13: 3 | F13: 4 | G13: 5 | H13: 6 | I13: 7 | J13: 8 | K13: 9 | L13: 10 | M13: 11 | N13: 12 | O13: 13 | P13: 14 | Q13: 15 | R13: 16 | S13: 17 | T13: 18 | U13: 19 | V13: 20
B14: =-'CAPEX 25%'!F14 -> -4836287.5 | C14: =$C$3 -> 787157 | D14: =$C$3 -> 787157 | E14: =$C$3 -> 787157 | F14: =$C$3 -> 787157 | G14: =$C$3 -> 787157 | H14: =$C$3 -> 787157 | I14: =$C$3 -> 787157 | J14: =$C$3 -> 787157 | ... V14: =$C$3 -> 787157
C17: LTO Batt Bank
B18: 0 | C18: 1 | D18: 2 | E18: 3 | F18: 4 | G18: 5 | H18: 6 | I18: 7 | J18: 8 | K18: 9 | L18: 10 | M18: 11 | N18: 12 | O18: 13 | P18: 14 | Q18: 15 | R18: 16 | S18: 17 | T18: 18 | U18: 19 | V18: 20
B19: =-'CAPEX 25%'!I14 -> -8076062.5 | C19: =$C$4 -> 976157 | D19: =$C$4 -> 976157 | E19: =$C$4 -> 976157 | F19: =$C$4 -> 976157 | G19: =$C$4 -> 976157 | H19: =$C$4 -> 976157 | I19: =$C$4 -> 976157 | J19: =$C$4 -> 976157 | ... V19: =$C$4 -> 976157

Sheet ROI 25%
B2: Lifespan | C2: 20 | E2: Cost NMC | F2: ='CAPEX 25%'!C11 -> 7377500 | H2: ROI NMC | I2: =F2/$C$4 -> 11.524517
B3: Discount Rate (%) | C3: 0 | E3: Cost LFP | F3: ='CAPEX 25%'!F11 -> 5172500 | H3: ROI LFP | I3: =F3/$C$5 -> 6.5711161
B4: Annual Profit NMC ($) | C4: ='OPEX 25%'!F19 -> 640157 | E4: Cost LTO | F4: ='CAPEX 25%'!I11 -> 8637500 | H4: ROI LTO | I4: =F4/$C$6 -> 8.8484742
B5: Annual Profit LFP ($) | C5: ='OPEX 25%'!I19 -> 787157
B6: Annual Profit LTO ($) | C6: ='OPEX 25%'!L19 -> 976157
C7: ROI NMC
B8: 0 | C8: 1 | D8: 2 | E8: 3 | F8: 4 | G8: 5 | H8: 6 | I8: 7 | J8: 8 | K8: 9 | L8: 10
B9: =-F2 -> -7377500 | C9: =$C$4/((1+$C$3)^C8)+B9 -> -6737343 | D9: =$C$4/((1+$C$3)^D8)+C9 -> -6097186 | E9: =$C$4/((1+$C$3)^E8)+D9 -> -5457029 | F9: =$C$4/((1+$C$3)^F8)+E9 -> -4816872 | G9: =$C$4/((1+$C$3)^G8)+F9 -> -4176715 | H9: =$C$4/((1+$C$3)^H8)+G9 -> -3536558 | I9: =$C$4/((1+$C$3)^I8)+H9 -> -2896401 | J9: =$C$4/((1+$C$3)^J8)+I9 -> -2256244 | ... L9: =$C$4/((1+$C$3)^L8)+K9 -> -975930
C12: 11 | D12: 12 | E12: 13 | F12: 14 | G12: 15 | H12: 16 | I12: 17 | J12: 18 | K12: 19 | L12: 20
C13: =$C$4/((1+$C$3)^C12)+L9 -> -335773 | D13: =$C$4/((1+$C$3)^D12)+C13 -> 304384 | E13: =$C$4/((1+$C$3)^E12)+D13 -> 944541 | F13: =$C$4/((1+$C$3)^F12)+E13 -> 1584698 | G13: =$C$4/((1+$C$3)^G12)+F13 -> 2224855 | H13: =$C$4/((1+$C$3)^H12)+G13 -> 2865012 | I13: =$C$4/((1+$C$3)^I12)+H13 -> 3505169 | J13: =$C$4/((1+$C$3)^J12)+I13 -> 4145326 | K13: =$C$4/((1+$C$3)^K12)+J13 -> 4785483 | L13: =$C$4/((1+$C$3)^L12)+K13 -> 5425640
C16: ROI LFP
B17: 0 | C17: 1 | D17: 2 | E17: 3 | F17: 4 | G17: 5 | H17: 6 | I17: 7 | J17: 8 | K17: 9 | L17: 10
B18: =-F3 -> -5172500 | C18: =$C$5/((1+$C$3)^C17)+B18 -> -4385343 | D18: =$C$5/((1+$C$3)^D17)+C18 -> -3598186 | E18: =$C$45/((1+$C$3)^E17)+D18 -> -3598186 | F18: =$C$5/((1+$C$3)^F17)+E18 -> -2811029 | G18: =$C$5/((1+$C$3)^G17)+F18 -> -2023872 | H18: =$C$5/((1+$C$3)^H17)+G18 -> -1236715 | I18: =$C$5/((1+$C$3)^I17)+H18 -> -449558 | J18: =$C$5/((1+$C$3)^J17)+I18 -> 337599 | K18: =$C$5/((1+$C$3)^K17)+J18 -> 1124756 | L18: =$C$5/((1+$C$3)^L17)+K18 -> 1911913
C21: 11 | D21: 12 | E21: 13 | F21: 14 | G21: 15 | H21: 16 | I21: 17 | J21: 18 | K21: 19 | L21: 20
C22: =$C$5/((1+$C$3)^C21)+L18 -> 2699070 | D22: =$C$5/((1+$C$3)^D21)+C22 -> 3486227 | E22: =$C$5/((1+$C$3)^E21)+D22 -> 4273384 | F22: =$C$5/((1+$C$3)^F21)+E22 -> 5060541 | G22: =$C$5/((1+$C$3)^G21)+F22 -> 5847698 | H22: =$C$5/((1+$C$3)^H21)+G22 -> 6634855 | I22: =$C$5/((1+$C$3)^I21)+H22 -> 7422012 | J22: =$C$5/((1+$C$3)^J21)+I22 -> 8209169 | K22: =$C$5/((1+$C$3)^K21)+J22 -> 8996326 | L22: =$C$5/((1+$C$3)^L21)+K22 -> 9783483
C26: ROI LTO
B27: 0 | C27: 1 | D27: 2 | E27: 3 | F27: 4 | G27: 5 | H27: 6 | I27: 7 | J27: 8 | K27: 9 | L27: 10
B28: =-F4 -> -8637500 | C28: =$C$6/((1+$C$3)^C27)+B28 -> -7661343 | D28: =$C$6/((1+$C$3)^D27)+C28 -> -6685186 | E28: =$C$6/((1+$C$3)^E27)+D28 -> -5709029 | F28: =$C$6/((1+$C$3)^F27)+E28 -> -4732872 | G28: =$C$6/((1+$C$3)^G27)+F28 -> -3756715 | H28: =$C$6/((1+$C$3)^H27)+G28 -> -2780558 | I28: =$C$6/((1+$C$3)^I27)+H28 -> -1804401 | J28: =$C$6/((1+$C$3)^J27)+I28 -> -828244 | ... L28: =$C$6/((1+$C$3)^L27)+K28 -> 1124070
C31: 11 | D31: 12 | E31: 13 | F31: 14 | G31: 15 | H31: 16 | I31: 17 | J31: 18 | K31: 19 | L31: 20
C32: =$C$6/((1+$C$3)^C31)+L28 -> 2100227 | D32: =$C$6/((1+$C$3)^D31)+C32 -> 3076384 | E32: =$C$6/((1+$C$3)^E31)+D32 -> 4052541 | F32: =$C$6/((1+$C$3)^F31)+E32 -> 5028698 | G32: =$C$6/((1+$C$3)^G31)+F32 -> 6004855 | H32: =$C$6/((1+$C$3)^H31)+G32 -> 6981012 | I32: =$C$6/((1+$C$3)^I31)+H32 -> 7957169 | J32: =$C$6/((1+$C$3)^J31)+I32 -> 8933326 | K32: =$C$6/((1+$C$3)^K31)+J32 -> 9909483 | L32: =$C$6/((1+$C$3)^L31)+K32 -> 10885640
